gazekit/__init__.py
gazekit/analyze.py
gazekit/aoi.py
gazekit/denoise.py
gazekit/hello.py
gazekit/plot.py
gazekit/sequence.py
gazekit/tools.py
tests/__init__.py
tests/test_aoi.py
gazekit-0.0.3.dist-info/LICENSE
gazekit-0.0.3.dist-info/METADATA
gazekit-0.0.3.dist-info/WHEEL
gazekit-0.0.3.dist-info/top_level.txt
gazekit-0.0.3.dist-info/RECORD
