Metadata-Version: 2.1
Name: gazekit
Version: 0.0.3
Summary: This is a Python library designed for processing eye-tracking data.
Home-page: https://github.com/CLaSLoVe/GazeKit
Author: CLaSLoVe
License: MIT
License-File: LICENSE
Requires-Dist: numpy (>=1.0)
Requires-Dist: pandas (>=2.0)
